s3vectorm/__init__.py
s3vectorm/_version.py
s3vectorm/api.py
s3vectorm/bucket.py
s3vectorm/index.py
s3vectorm/metadata.py
s3vectorm/paths.py
s3vectorm/vector.py
s3vectorm/vendor/__init__.py
s3vectorm/vendor/pytest_cov_helper.py
s3vectorm-0.1.1.dist-info/AUTHORS.rst
s3vectorm-0.1.1.dist-info/LICENSE.txt
s3vectorm-0.1.1.dist-info/METADATA
s3vectorm-0.1.1.dist-info/WHEEL
s3vectorm-0.1.1.dist-info/RECORD
